Hub/__init__.py
Hub/main.py
Hub/external/__init__.py
Hub/internal/__init__.py
Hub/internal/prophandler.py
Hub/internal/subvoicerec.py
Project0-0.1.4.dist-info/LICENSE
Project0-0.1.4.dist-info/METADATA
Project0-0.1.4.dist-info/WHEEL
Project0-0.1.4.dist-info/entry_points.txt
Project0-0.1.4.dist-info/top_level.txt
Project0-0.1.4.dist-info/RECORD
