Metadata-Version: 2.1
Name: Project0
Version: 0.1.4
Summary: Offline vocal assistant and tts
Home-page: http://github.com/fenrir77/project0
Author: Fenrir77
Author-email: fenrir7377@gmail.com
License: MIT
Keywords: vocal assistant offline tts
Platform: UNKNOWN
Classifier: Development Status :: 1 - Planning
Classifier: Intended Audience :: Developers
Classifier: License :: OSI Approved :: MIT License
Classifier: Programming Language :: Python :: 3.7
Classifier: Topic :: Multimedia :: Sound/Audio :: Capture/Recording
Classifier: Topic :: Multimedia :: Sound/Audio :: Speech
Classifier: Topic :: Text Processing
Classifier: Natural Language :: English
Classifier: Natural Language :: Italian
Requires-Dist: PocketSphinx
Requires-Dist: PyAudio
Requires-Dist: SpeechRecognition
Requires-Dist: markdown
Requires-Dist: pyttsx3
